frequenz.libs/libgcc_s-39080030.so.1
frequenz/microgrid_component_graph/__init__.py
frequenz/microgrid_component_graph/__init__.pyi
frequenz/microgrid_component_graph/_component_graph.cpython-313t-aarch64-linux-musl.so
frequenz/microgrid_component_graph/conftest.py
frequenz/microgrid_component_graph/py.typed
frequenz_microgrid_component_graph-0.3.4.dist-info/METADATA
frequenz_microgrid_component_graph-0.3.4.dist-info/WHEEL
frequenz_microgrid_component_graph-0.3.4.dist-info/licenses/LICENSE
frequenz_microgrid_component_graph-0.3.4.dist-info/RECORD
